LICENSE
MANIFEST.in
README.md
requirements.txt
setup.py
bin/depccg_en
bin/depccg_ja
c/Makefile
c/morpha.c
c/morpha.h
depccg/__init__.py
depccg/__main__.py
depccg/annotator.py
depccg/argparse.py
depccg/cat.py
depccg/instance_models.py
depccg/lang.py
depccg/morpha.pyx
depccg/parsing.h
depccg/parsing.py
depccg/parsing.pyx
depccg/tree.py
depccg/types.py
depccg/unification.py
depccg/utils.py
depccg.egg-info/PKG-INFO
depccg.egg-info/SOURCES.txt
depccg.egg-info/dependency_links.txt
depccg.egg-info/not-zip-safe
depccg.egg-info/requires.txt
depccg.egg-info/top_level.txt
depccg/allennlp/__init__.py
depccg/allennlp/supertagger.py
depccg/allennlp/utils.py
depccg/allennlp/dataset/__init__.py
depccg/allennlp/dataset/ccgbank_as_ptb.py
depccg/allennlp/dataset/ja_supertagging_dataset.py
depccg/allennlp/dataset/supertagging_dataset.py
depccg/allennlp/models/__init__.py
depccg/allennlp/models/supertagger.py
depccg/allennlp/nn/__init__.py
depccg/allennlp/nn/afix_embedding.py
depccg/allennlp/nn/bilinear.py
depccg/allennlp/predictor/__init__.py
depccg/allennlp/predictor/parser_predictor.py
depccg/allennlp/predictor/supertagger_predictor.py
depccg/chainer/__init__.py
depccg/chainer/biaffine.py
depccg/chainer/fixed_length_n_step_lstm.py
depccg/chainer/ja_lstm_parser_bi.py
depccg/chainer/lstm_parser_bi_fast.py
depccg/chainer/param.py
depccg/chainer/supertagger.py
depccg/grammar/__init__.py
depccg/grammar/en.py
depccg/grammar/ja.py
depccg/models/__init__.py
depccg/models/cat_dict.en.jsonnet
depccg/models/chars.ja.jsonnet
depccg/models/config_en.jsonnet
depccg/models/config_ja.jsonnet
depccg/models/config_rebank.jsonnet
depccg/models/prefixes.en.jsonnet
depccg/models/seen_rules.en.jsonnet
depccg/models/seen_rules.en_rebank.jsonnet
depccg/models/seen_rules.ja.jsonnet
depccg/models/semantic_templates_en_event.yaml
depccg/models/semantic_templates_ja_event.yaml
depccg/models/suffixes.en.jsonnet
depccg/models/targets.en.jsonnet
depccg/models/targets.en_rebank.jsonnet
depccg/models/targets.ja.jsonnet
depccg/models/tokens.en.jsonnet
depccg/models/tokens.ja.jsonnet
depccg/models/unary_rules.en.jsonnet
depccg/models/unary_rules.ja.jsonnet
depccg/models/verbstem.list
