Metadata-Version: 2.1
Name: depccg
Version: 2.0.3.2
Summary: A parser for natural language based on combinatory categorial grammar
Home-page: https://github.com/masashi-y/depccg
Author: Masashi Yoshikawa
Author-email: yoshikawa@tohoku.ac.jp
License: MIT License
Platform: UNKNOWN
Classifier: License :: OSI Approved :: MIT License
Classifier: Programming Language :: Python :: 3.5
Classifier: Programming Language :: Python :: 3.6
